MANIFEST.in
README.rst
setup.py
mdesc/__init__.py
mdesc/base.py
mdesc/eval.py
mdesc/html_error.txt
mdesc/html_sensitivity.txt
mdesc/version.py
mdesc/utils/__init__.py
mdesc/utils/categorical_conversions.py
mdesc/utils/check_utils.py
mdesc/utils/fmt_model_outputs.py
mdesc/utils/formatting.py
mdesc/utils/percentiles.py
mdesc/utils/utils.py
model_describer.egg-info/PKG-INFO
model_describer.egg-info/SOURCES.txt
model_describer.egg-info/dependency_links.txt
model_describer.egg-info/top_level.txt