Metadata-Version: 1.1
Name: model-describer
Version: 0.1.2.2
Summary: How can I unlock what my model is thinking? model-describer helps answer this problem for sklearn machine learning models. Specifically, model-describer helps address two key issues: error and model sensitivity. For error, model-describer analyzes how well the model is performing within key regions of the data in a visually compelling way. For sensitivity, model-describer identifies what parts of different variable distributions have the biggest impact on model predictions and plots the
Home-page: https://github.com/DataScienceSquad/model-describer
Author: Jason Lewris, Venkat Gangavarapu, Daniel Byler,  Shruti Panda
Author-email: jlewris@deloitte.com, vegangavarapu@deloitte.com, dybler@deloitte.com, shrupanda@deloitte.com
License: MIT
Download-URL: https://github.com/DataScienceSquad/model-describer/archive/0.1.2.2.zip
Keywords: machine learning,data science,sklearn,scikit-learn,machine learning interpretability,visualization
Platform: UNKNOWN
Classifier: License :: OSI Approved :: MIT License
Classifier: Programming Language :: Python :: 2.7
Classifier: Programming Language :: Python :: 3.5
Classifier: Programming Language :: Python :: 3.6
Classifier: Development Status :: 4 - Beta
Classifier: Intended Audience :: Developers
Classifier: Intended Audience :: Education
Classifier: Operating System :: Microsoft :: Windows
Classifier: Operating System :: MacOS
Classifier: Operating System :: POSIX :: Linux
Classifier: Topic :: Communications :: Email
Classifier: Topic :: Education
Classifier: Topic :: Scientific/Engineering
Classifier: Topic :: Scientific/Engineering :: Visualization
Classifier: Topic :: Scientific/Engineering :: Mathematics
Classifier: Topic :: Scientific/Engineering :: Artificial Intelligence
